galaxyls/__init__.py
galaxyls/__main__.py
galaxyls/config.py
galaxyls/constants.py
galaxyls/server.py
galaxyls/types.py
galaxyls/utils.py
galaxyls/version.py
galaxyls/services/__init__.py
galaxyls/services/completion.py
galaxyls/services/context.py
galaxyls/services/definitions.py
galaxyls/services/format.py
galaxyls/services/language.py
galaxyls/services/links.py
galaxyls/services/macros.py
galaxyls/services/references.py
galaxyls/services/symbols.py
galaxyls/services/validation.py
galaxyls/services/tools/__init__.py
galaxyls/services/tools/common.py
galaxyls/services/tools/constants.py
galaxyls/services/tools/document.py
galaxyls/services/tools/inputs.py
galaxyls/services/tools/iuc.py
galaxyls/services/tools/linting.py
galaxyls/services/tools/macros.py
galaxyls/services/tools/refactor.py
galaxyls/services/tools/testing.py
galaxyls/services/tools/generators/__init__.py
galaxyls/services/tools/generators/command.py
galaxyls/services/tools/generators/snippets.py
galaxyls/services/tools/generators/tests.py
galaxyls/services/xml/__init__.py
galaxyls/services/xml/constants.py
galaxyls/services/xml/document.py
galaxyls/services/xml/nodes.py
galaxyls/services/xml/parser.py
galaxyls/services/xml/scanner.py
galaxyls/services/xml/types.py
galaxyls/services/xml/utils.py
galaxyls/services/xsd/__init__.py
galaxyls/services/xsd/constants.py
galaxyls/services/xsd/parser.py
galaxyls/services/xsd/service.py
galaxyls/services/xsd/types.py
galaxyls/services/xsd/validation.py
galaxy_language_server-0.14.1.dist-info/METADATA
galaxy_language_server-0.14.1.dist-info/WHEEL
galaxy_language_server-0.14.1.dist-info/top_level.txt
galaxy_language_server-0.14.1.dist-info/RECORD
