Metadata-Version: 2.4
Name: galaxy-language-server
Version: 0.14.1
Summary: A language server for Galaxy (https://galaxyproject.org) tool wrappers
Home-page: https://github.com/davelopez/galaxy-language-server/tree/main/server
Author: David López
Author-email: davelopez7391@gmail.com
License: Apache-2.0
Keywords: galaxy,python,language server
Classifier: Development Status :: 5 - Production/Stable
Classifier: Intended Audience :: Developers
Classifier: Intended Audience :: Information Technology
Classifier: Topic :: Software Development :: Libraries :: Python Modules
Classifier: Operating System :: OS Independent
Classifier: Programming Language :: Python :: 3 :: Only
Classifier: Programming Language :: Python :: 3.9
Classifier: Programming Language :: Python :: 3.10
Classifier: Programming Language :: Python :: 3.11
Classifier: Programming Language :: Python :: 3.12
Classifier: Programming Language :: Python :: 3.13
Requires-Python: >=3.9
Requires-Dist: pygls==1.3.1
Requires-Dist: lxml==6.0.1
Requires-Dist: anytree==2.13.0
Requires-Dist: galaxy-tool-util==25.0.2
Requires-Dist: edam-ontology==1.25.2
Dynamic: author
Dynamic: author-email
Dynamic: classifier
Dynamic: description
Dynamic: description-content-type
Dynamic: home-page
Dynamic: keywords
Dynamic: license
Dynamic: requires-dist
Dynamic: requires-python
Dynamic: summary
